ratelimit-stubs/__init__.pyi
ratelimit-stubs/decorators.pyi
ratelimit-stubs/exception.pyi
ratelimit-stubs/utils.pyi
ratelimit_stubs-2.2.1.dist-info/METADATA
ratelimit_stubs-2.2.1.dist-info/WHEEL
ratelimit_stubs-2.2.1.dist-info/top_level.txt
ratelimit_stubs-2.2.1.dist-info/RECORD
