Metadata-Version: 2.1
Name: ratelimit-stubs
Version: 2.2.1
Summary: Stub for ratelimit
Home-page: https://github.com/isac322/ratelimit-stubs
Author: Byeonghoon Yoo
Author-email: bh322yoo@gmail.com
License: MIT
Keywords: ratelimit,api,decorator
Platform: UNKNOWN
Classifier: Development Status :: 5 - Production/Stable
Classifier: Intended Audience :: Developers
Classifier: License :: OSI Approved :: MIT License
Classifier: Natural Language :: English
Classifier: Programming Language :: Python
Classifier: Topic :: Software Development
